model/VERSION
model/__init__.py
model/config.yml
model/pipeline.py
model/predict.py
model/train_pipeline.py
model/config/__init__.py
model/config/core.py
model/datasets/__init__.py
model/datasets/test.csv
model/datasets/train.csv
model/processing/__init__.py
model/processing/data_manager.py
model/processing/features.py
model/processing/validation.py
model/trained_models/model_output_v0.0.6.pkl
tid_CICDS_model-0.0.6.dist-info/METADATA
tid_CICDS_model-0.0.6.dist-info/WHEEL
tid_CICDS_model-0.0.6.dist-info/top_level.txt
tid_CICDS_model-0.0.6.dist-info/RECORD
