Metadata-Version: 2.1
Name: tid-CICDS-model
Version: 0.0.6
Summary: Example model package using CICDS Data.
Home-page: UNKNOWN
Author: VidhyaS
License: BSD-3
Platform: UNKNOWN
Classifier: License :: OSI Approved :: MIT License
Classifier: Programming Language :: Python
Classifier: Programming Language :: Python :: 3
Classifier: Programming Language :: Python :: 3.6
Classifier: Programming Language :: Python :: 3.7
Classifier: Programming Language :: Python :: 3.8
Classifier: Programming Language :: Python :: 3.9
Classifier: Programming Language :: Python :: Implementation :: CPython
Classifier: Programming Language :: Python :: Implementation :: PyPy
Requires-Python: >=3.6.0
Requires-Dist: pydantic
Requires-Dist: strictyaml
Requires-Dist: ruamel.yaml
Requires-Dist: feature-engine
Requires-Dist: joblib
